simple_meta/__init__.py
simple_meta/__main__.py
simple_metagenomics-1.0.6.dist-info/METADATA
simple_metagenomics-1.0.6.dist-info/WHEEL
simple_metagenomics-1.0.6.dist-info/entry_points.txt
simple_metagenomics-1.0.6.dist-info/top_level.txt
simple_metagenomics-1.0.6.dist-info/RECORD
