Metadata-Version: 2.1
Name: simple-metagenomics
Version: 1.0.6
Summary: metagenomics pipline for BIOF501
Home-page: https://github.com/Tony-xy-Liu/simple-metagenomics
Author: Tony Liu
Author-email: contacttonyliu@gmail.com
License: UNKNOWN
Project-URL: Bug Tracker, https://github.com/Tony-xy-Liu/simple-metagenomics/issues
Platform: UNKNOWN
Classifier: Programming Language :: Python :: 3
Classifier: Operating System :: OS Independent
Requires-Python: >=3.6
